FortranRNG.cpython-310-darwin.so
FortranRNG-1.5.1.dist-info/LICENSE
FortranRNG-1.5.1.dist-info/METADATA
FortranRNG-1.5.1.dist-info/WHEEL
FortranRNG-1.5.1.dist-info/top_level.txt
FortranRNG-1.5.1.dist-info/RECORD
