Metadata-Version: 2.1
Name: FortranRNG
Version: 1.5.1
Summary: Fortran RNG for Python3
Home-page: https://github.com/BrokenShell/FortranRNG-API/tree/main/FortranRNG
Author: Robert Sharp
Author-email: webmaster@sharpdesigndigital.com
License: Free for non-commercial use
Keywords: FortranRNG,High Performance Random Value Toolkit,percent true,d,dice,random below,random integer,random range,plus or minus,plus of minus linear,canonical,random float,triangular,ZeroCool Algorithms,random index,front linear,middle linear,back linear,quantum linear
Platform: Darwin
Platform: Linux
Platform: Windows
Classifier: Development Status :: 5 - Production/Stable
Classifier: Programming Language :: Python :: 3.7
Classifier: Programming Language :: Fortran
Classifier: Operating System :: MacOS :: MacOS X
Classifier: Operating System :: POSIX :: Linux
Classifier: Operating System :: Microsoft :: Windows
Classifier: Topic :: Software Development :: Libraries :: Python Modules
Requires-Python: >=3.7
License-File: LICENSE
Requires-Dist: numpy
